MANIFEST.in
README.md
setup.py
pyavroc/__init__.py
pyavroc/_version.py
pyavroc.egg-info/PKG-INFO
pyavroc.egg-info/SOURCES.txt
pyavroc.egg-info/dependency_links.txt
pyavroc.egg-info/top_level.txt
pyavroc/avro/NOTICE.txt
src/avroenum.c
src/avroenum.h
src/convert.c
src/convert.h
src/deserializer.c
src/deserializer.h
src/error.c
src/error.h
src/filereader.c
src/filereader.h
src/filewriter.c
src/filewriter.h
src/pyavro.c
src/record.c
src/record.h
src/serializer.c
src/serializer.h
src/util.c
src/util.h