Metadata-Version: 1.1
Name: pyavroc
Version: 0.7.2
Summary: Avro file reader/writer
Home-page: http://github.com/Byhiras/pyavroc
Author: Ben Walsh
Author-email: ben.walsh@byhiras.com
License: Apache License 2.0
Keywords: avro serialization
Platform: any
Classifier: Development Status :: 4 - Beta
Classifier: Intended Audience :: Developers
Classifier: License :: OSI Approved :: Apache Software License
Classifier: Programming Language :: Python
Classifier: Programming Language :: Python :: 2
Classifier: Topic :: Software Development :: Libraries
Classifier: Topic :: Software Development :: Libraries :: Python Modules
